distro.py
distro-1.3.0.dist-info/DESCRIPTION.rst
distro-1.3.0.dist-info/LICENSE.txt
distro-1.3.0.dist-info/METADATA
distro-1.3.0.dist-info/RECORD
distro-1.3.0.dist-info/WHEEL
distro-1.3.0.dist-info/entry_points.txt
distro-1.3.0.dist-info/metadata.json
distro-1.3.0.dist-info/top_level.txt
